README.rst
setup.py
django_model_i18n.egg-info/PKG-INFO
django_model_i18n.egg-info/SOURCES.txt
django_model_i18n.egg-info/dependency_links.txt
django_model_i18n.egg-info/requires.txt
django_model_i18n.egg-info/top_level.txt
model_i18n/__init__.py
model_i18n/admin.py
model_i18n/admin_helpers.py
model_i18n/conf.py
model_i18n/decorators.py
model_i18n/exceptions.py
model_i18n/loaders.py
model_i18n/managers.py
model_i18n/models.py
model_i18n/options.py
model_i18n/patches.py
model_i18n/query.py
model_i18n/translator.py
model_i18n/urls.py
model_i18n/utils.py
model_i18n/validation.py
model_i18n/views.py
model_i18n/locale/es/LC_MESSAGES/django.po
model_i18n/templates/i18n/admin/change_form.html
model_i18n/templates/i18n/admin/change_translation_form.html
model_i18n/templates/i18n/admin/edit_inline.html
model_i18n/templates/i18n/admin/language_links.html
model_i18n/templatetags/__init__.py
model_i18n/templatetags/model_i18n_tags.py