Metadata-Version: 1.1
Name: django-model-i18n
Version: 0.5.1
Summary: django-model-i18n is a django application that tries to make multilingual data in models less painful.
Home-page: https://github.com/juanpex/django-model-i18n
Author: juanpex
Author-email: jpma55@gmail.com
License: BSD
Download-URL: https://github.com/juanpex/django-model-i18n/zipball/master/
Keywords: django,model,i18n,translation,translations,python,pluggable
Platform: UNKNOWN
Classifier: Framework :: Django
Classifier: Development Status :: 3 - Alpha
Classifier: Topic :: Internet
Classifier: License :: OSI Approved :: BSD License
Classifier: Intended Audience :: Developers
Classifier: Environment :: Web Environment
Classifier: Programming Language :: Python :: 2.5
Classifier: Programming Language :: Python :: 2.6
Classifier: Programming Language :: Python :: 2.7
